coderadar/__init__.py
coderadar/__main__.py
coderadar/_functions.py
coderadar/flake8.py
coderadar/git.py
coderadar/gitlab.py
coderadar/inspector.py
coderadar/pylint.py
coderadar/pytest.py
coderadar/report.py
coderadar/templates/__init__.py
coderadar/templates/report.html
coderadar/templates/report.txt
coderadar/templates/report_py23.html
coderadar/templates/report_py23.txt
coderadar/tests/.coverage
tests/__init__.py
tests/code_quality_report.html
tests/code_quality_report.txt
tests/test_coderadar.py
tests/test_main.py
tests/test_pylint.py
tests/test_pytest.py
tests/test_report.py
coderadar-0.5.9.dist-info/LICENSE
coderadar-0.5.9.dist-info/METADATA
coderadar-0.5.9.dist-info/WHEEL
coderadar-0.5.9.dist-info/entry_points.txt
coderadar-0.5.9.dist-info/top_level.txt
coderadar-0.5.9.dist-info/RECORD
