Metadata-Version: 2.1
Name: coderadar
Version: 0.5.9
Summary: Identifying the highest threats to your code quality by analyzing code metrics of your project using pytest and pylint.
Author: Carsten König
License: GNU GPLv3 License
Project-URL: Homepage, https://gitlab.com/ck2go/coderadar
Keywords: metrics,code quality,CI/CD,lint
Classifier: Development Status :: 4 - Beta
Classifier: Intended Audience :: Developers
Classifier: License :: OSI Approved :: GNU General Public License v3 (GPLv3)
Classifier: Topic :: Software Development
Classifier: Programming Language :: Python
Classifier: Programming Language :: Python :: 2.7
Classifier: Programming Language :: Python :: 3
Classifier: Operating System :: Unix
Classifier: Operating System :: POSIX
Classifier: Operating System :: MacOS
Requires-Python: >=2.7
License-File: LICENSE
Requires-Dist: pytest
Requires-Dist: pytest-mock
Requires-Dist: pytest-cov
Requires-Dist: pylint
